cars/__init__.py
cars/bmw.py
cars/fiat.py
cars/sample.py
cars/volvo.py
shopping/__init__.py
shopping/car_list.py
shopping/order.py
pack_carlist-0.0.1.dist-info/LICENSE.txt
pack_carlist-0.0.1.dist-info/METADATA
pack_carlist-0.0.1.dist-info/WHEEL
pack_carlist-0.0.1.dist-info/top_level.txt
pack_carlist-0.0.1.dist-info/RECORD
