Metadata-Version: 2.1
Name: pack-carlist
Version: 0.0.1
Summary: Training example on how to upload package to PyPi
Home-page: UNKNOWN
Author: mvsa
Author-email: daniel.galea@xomnia.com
License: UNKNOWN
Platform: UNKNOWN
Classifier: Programming Language :: Python :: 3
Classifier: License :: OSI Approved :: MIT License
Classifier: Operating System :: OS Independent
Requires-Python: >=3.6
